nextdnsapi/__init__.py
nextdnsapi/api.py
nextdnsapi-1.7.2.dist-info/LICENSE
nextdnsapi-1.7.2.dist-info/METADATA
nextdnsapi-1.7.2.dist-info/WHEEL
nextdnsapi-1.7.2.dist-info/top_level.txt
nextdnsapi-1.7.2.dist-info/RECORD
