Metadata-Version: 2.1
Name: nextdnsapi
Version: 1.7.2
Summary: I was getting increasingly frustrated with NextDNS's lack of API. I wanted to manage things on the fly. So, I did the most logical thing. I built a python script (library-to-be) to control my NextDNS account. I decided to make it public because why not?
Home-page: https://github.com/rhijjawi/NextDNS-API
Author-email: erpihmisr@relay.firefox.com
License: MIT
Download-URL: https://github.com/rhijjawi/NextDNS-API/archivev1-7-0.tar.gz
Keywords: NEXTDNS,API,REQUESTS
Platform: UNKNOWN
Classifier: Development Status :: 5 - Production/Stable
Classifier: Intended Audience :: Developers
Classifier: Topic :: Software Development :: Build Tools
Classifier: License :: OSI Approved :: MIT License
Classifier: Programming Language :: Python :: 3
Classifier: Programming Language :: Python :: 3.4
Classifier: Programming Language :: Python :: 3.5
Classifier: Programming Language :: Python :: 3.6
License-File: LICENSE
Requires-Dist: requests
